napari_UniSPAC/__init__.py
napari_UniSPAC/_widget.py
napari_UniSPAC/napari.yaml
napari_UniSPAC/segNeuro.py
napari_UniSPAC/slicer.py
napari_UniSPAC/unet2d.py
napari_UniSPAC/unet3d.py
napari_unispac-1.0.6.dist-info/licenses/LICENSE
napari_unispac-1.0.6.dist-info/METADATA
napari_unispac-1.0.6.dist-info/WHEEL
napari_unispac-1.0.6.dist-info/entry_points.txt
napari_unispac-1.0.6.dist-info/top_level.txt
napari_unispac-1.0.6.dist-info/RECORD
